[
  {
    "id": 101,
    "name": "1",
    "imageUrl": "images/1.jpg"
  },
  {
    "id": 102,
    "name": "2",
    "imageUrl": "images/2.jpg"
  },
  {
    "id": 103,
    "name": "3",
    "imageUrl": "images/3.jpg"
  },
  {
    "id": 104,
    "name": "4",
    "imageUrl": "images/4.jpg"
  },
  {
    "id": 105,
    "name": "5",
    "imageUrl": "images/5.jpg"
  },
  {
    "id": 106,
    "name": "6",
    "imageUrl": "images/6.jpg"
  },
  {
    "id": 107,
    "name": "7",
    "imageUrl": "images/7.jpg"
  },
  {
    "id": 108,
    "name": "8",
    "imageUrl": "images/8.jpg"
  },
  {
    "id": 109,
    "name": "9",
    "imageUrl": "images/9.jpg"
  },
  {
    "id": 110,
    "name": "10",
    "imageUrl": "images/10.jpg"
  },
  {
    "id": 111,
    "name": "11",
    "imageUrl": "images/11.jpg"
  },
  {
    "id": 112,
    "name": "12",
    "imageUrl": "images/12.jpg"
  },
  {
    "id": 113,
    "name": "13",
    "imageUrl": "images/13.jpg"
  },
  {
    "id": 114,
    "name": "14",
    "imageUrl": "images/14.jpg"
  },
  {
    "id": 115,
    "name": "15",
    "imageUrl": "images/15.jpg"
  }
]